strto/__init__.py
strto/core.py
strto/parsers.py
strto/utils.py
strto-0.2.6.dist-info/METADATA
strto-0.2.6.dist-info/WHEEL
strto-0.2.6.dist-info/licenses/LICENSE
strto-0.2.6.dist-info/RECORD
