Metadata-Version: 2.4
Name: strto
Version: 0.2.6
Summary: Type-guided parsing library for converting strings to Python objects
Project-URL: Repository, https://github.com/zigai/strto
Project-URL: Issues, https://github.com/zigai/strto/issues
Project-URL: Homepage, https://github.com/zigai/strto
Author-email: Žiga Ivanšek <ziga.ivansek@gmail.com>
License: MIT License
License-File: LICENSE
Keywords: parser,parsing,python object parser,python string parser,python string to object,python type hint parser,string parsing,type-conversion,type-hints
Classifier: Intended Audience :: Developers
Classifier: License :: OSI Approved :: MIT License
Classifier: Operating System :: OS Independent
Classifier: Programming Language :: Python
Classifier: Programming Language :: Python :: 3
Classifier: Programming Language :: Python :: 3 :: Only
Classifier: Programming Language :: Python :: 3.10
Classifier: Programming Language :: Python :: 3.11
Classifier: Programming Language :: Python :: 3.12
Classifier: Programming Language :: Python :: 3.13
Classifier: Programming Language :: Python :: 3.14
Classifier: Topic :: Software Development :: Libraries :: Python Modules
Classifier: Topic :: Text Processing
Classifier: Topic :: Utilities
Classifier: Typing :: Typed
Requires-Python: >=3.10
Requires-Dist: objinspect>=0.4.1
Requires-Dist: stdl>=0.6.8
Provides-Extra: dev
Requires-Dist: codespell; extra == 'dev'
Requires-Dist: coverage; extra == 'dev'
Requires-Dist: mypy; extra == 'dev'
Requires-Dist: pre-commit; extra == 'dev'
Requires-Dist: pydantic>=2; extra == 'dev'
Requires-Dist: pytest; extra == 'dev'
Requires-Dist: ruff; extra == 'dev'
Provides-Extra: test
Requires-Dist: coverage; extra == 'test'
Requires-Dist: pydantic>=2; extra == 'test'
Requires-Dist: pytest; extra == 'test'
